{
    "integration_keys": {
        "description": "Chaves usadas para integrar SNCR e CAFIR pelo código do imóvel no Incra.",
        "mapping": [
            {
                "left": {
                    "database": "SNCR",
                    "table": "tbimovel_ac",
                    "column": "codigo"
                },
                "right": {
                    "database": "CAFIR",
                    "table": "tbimovel_ac",
                    "column": "codigo_incra"
                },
                "semantics": "Ambos representam o código do imóvel no Incra."
            }
        ]
    },
    "databases": [
        {
            "name": "CAFIR",
            "description": "Cadastro de Imóveis Rurais (CAFIR), Receita Federal do Brasil.",
            "tables": [
                {
                    "name": "tbimovel_ac",
                    "description": "Tabela principal do cadastro de imóveis rurais (CAFIR).",
                    "columns": [
                        {
                            "name": "nirf",
                            "description": "Número do imóvel na RFB (NIRF)."
                        },
                        {
                            "name": "area",
                            "description": "Área total do imóvel (ha)."
                        },
                        {
                            "name": "codigo_incra",
                            "description": "Código do imóvel no Incra (chave de integração com SNCR)."
                        },
                        {
                            "name": "nome",
                            "description": "Denominação do imóvel rural."
                        },
                        {
                            "name": "situacao",
                            "description": "Situação cadastral no CAFIR (ex.: ativo)."
                        },
                        {
                            "name": "uf",
                            "description": "Unidade Federativa do imóvel."
                        },
                        {
                            "name": "cep",
                            "description": "CEP de localização do imóvel."
                        },
                        {
                            "name": "atualizacao",
                            "description": "Data da última atualização no CAFIR."
                        },
                        {
                            "name": "isento",
                            "description": "Indicador de isenção no âmbito da RFB."
                        }
                    ]
                }
            ]
        },
        {
            "name": "SNCR",
            "description": "Sistema Nacional de Cadastro Rural (SNCR), gerido pelo Incra.",
            "tables": [
                {
                    "name": "tbimovel_ac",
                    "description": "Cadastro de imóveis rurais no SNCR/Incra.",
                    "columns": [
                        {
                            "name": "codigo",
                            "description": "Código do imóvel no Incra (chave de integração com CAFIR)."
                        },
                        {
                            "name": "nome",
                            "description": "Denominação do imóvel rural."
                        },
                        {
                            "name": "municipio_ibge",
                            "description": "Código IBGE do município do imóvel."
                        },
                        {
                            "name": "area",
                            "description": "Área total do imóvel (ha)."
                        },
                        {
                            "name": "natureza",
                            "description": "Natureza jurídica do imóvel."
                        }
                    ]
                },
                {
                    "name": "tbmunicipio_ac",
                    "description": "Municípios associados aos imóveis cadastrados.",
                    "columns": [
                        {
                            "name": "codigo_ibge",
                            "description": "Código do município (IBGE)."
                        },
                        {
                            "name": "municipio",
                            "description": "Nome oficial do município."
                        }
                    ]
                },
                {
                    "name": "tbtitular_ac",
                    "description": "Titulares (PF/PJ) dos imóveis rurais.",
                    "columns": [
                        {
                            "name": "id",
                            "description": "Identificador do titular."
                        },
                        {
                            "name": "imovel",
                            "description": "Código do imóvel (referência a tbimovel_ac.codigo)."
                        },
                        {
                            "name": "nome_pessoa",
                            "description": "Nome da pessoa titular."
                        },
                        {
                            "name": "condicao",
                            "description": "Condição/vínculo com o imóvel (ex.: proprietário, posseiro)."
                        },
                        {
                            "name": "percentual",
                            "description": "Percentual de direito/participação no imóvel."
                        }
                    ]
                }
            ]
        }
    ]
}